odoo/addons/despatch_advice_import_ubl/README.rst
odoo/addons/despatch_advice_import_ubl/__init__.py
odoo/addons/despatch_advice_import_ubl/__manifest__.py
odoo/addons/despatch_advice_import_ubl/i18n/despatch_advice_import_ubl.pot
odoo/addons/despatch_advice_import_ubl/i18n/es.po
odoo/addons/despatch_advice_import_ubl/i18n/fr.po
odoo/addons/despatch_advice_import_ubl/i18n/it.po
odoo/addons/despatch_advice_import_ubl/readme/CONTRIBUTORS.rst
odoo/addons/despatch_advice_import_ubl/readme/CREDITS.rst
odoo/addons/despatch_advice_import_ubl/readme/DESCRIPTION.rst
odoo/addons/despatch_advice_import_ubl/static/description/icon.png
odoo/addons/despatch_advice_import_ubl/static/description/index.html
odoo/addons/despatch_advice_import_ubl/tests/__init__.py
odoo/addons/despatch_advice_import_ubl/tests/test_despatch_advice_import.py
odoo/addons/despatch_advice_import_ubl/tests/test_despatch_advice_mix.py
odoo/addons/despatch_advice_import_ubl/tests/files/despatch_advice_2.xml
odoo/addons/despatch_advice_import_ubl/tests/files/despatch_advice_tmpl.xml
odoo/addons/despatch_advice_import_ubl/tests/files/do_mix1.xml
odoo/addons/despatch_advice_import_ubl/tests/files/do_mix2.xml
odoo/addons/despatch_advice_import_ubl/wizard/__init__.py
odoo/addons/despatch_advice_import_ubl/wizard/despatch_advice_import.py
odoo_addon_despatch_advice_import_ubl-16.0.1.1.0.dist-info/METADATA
odoo_addon_despatch_advice_import_ubl-16.0.1.1.0.dist-info/WHEEL
odoo_addon_despatch_advice_import_ubl-16.0.1.1.0.dist-info/top_level.txt
odoo_addon_despatch_advice_import_ubl-16.0.1.1.0.dist-info/RECORD
