Metadata-Version: 2.1
Name: odoo-addon-despatch-advice-import-ubl
Version: 16.0.1.1.0
Summary: Import Despatch Advice files
Home-page: https://github.com/OCA/edi
Author: ACSONE SA/NV,Odoo Community Association (OCA)
Author-email: support@odoo-community.org
License: AGPL-3
Platform: UNKNOWN
Classifier: Programming Language :: Python
Classifier: Framework :: Odoo
Classifier: Framework :: Odoo :: 16.0
Classifier: License :: OSI Approved :: GNU Affero General Public License v3
Requires-Python: >=3.10
Requires-Dist: odoo-addon-base-ubl <16.1dev,>=16.0dev
Requires-Dist: odoo-addon-despatch-advice-import <16.1dev,>=16.0dev
Requires-Dist: odoo <16.1dev,>=16.0a
